jsonpath_rfc9535/__about__.py
jsonpath_rfc9535/__init__.py
jsonpath_rfc9535/__main__.py
jsonpath_rfc9535/cli.py
jsonpath_rfc9535/environment.py
jsonpath_rfc9535/exceptions.py
jsonpath_rfc9535/filter_expressions.py
jsonpath_rfc9535/lex.py
jsonpath_rfc9535/node.py
jsonpath_rfc9535/parse.py
jsonpath_rfc9535/py.typed
jsonpath_rfc9535/query.py
jsonpath_rfc9535/segments.py
jsonpath_rfc9535/selectors.py
jsonpath_rfc9535/serialize.py
jsonpath_rfc9535/tokens.py
jsonpath_rfc9535/function_extensions/__init__.py
jsonpath_rfc9535/function_extensions/_pattern.py
jsonpath_rfc9535/function_extensions/count.py
jsonpath_rfc9535/function_extensions/filter_function.py
jsonpath_rfc9535/function_extensions/length.py
jsonpath_rfc9535/function_extensions/match.py
jsonpath_rfc9535/function_extensions/search.py
jsonpath_rfc9535/function_extensions/value.py
jsonpath_rfc9535/utils/__init__.py
jsonpath_rfc9535/utils/nondeterministic_descent.py
jsonpath_rfc9535-0.1.6.dist-info/METADATA
jsonpath_rfc9535-0.1.6.dist-info/WHEEL
jsonpath_rfc9535-0.1.6.dist-info/entry_points.txt
jsonpath_rfc9535-0.1.6.dist-info/licenses/LICENSE.txt
jsonpath_rfc9535-0.1.6.dist-info/RECORD
