Metadata-Version: 2.4
Name: jsonpath-rfc9535
Version: 0.1.6
Summary: RFC 9535 - JSONPath: Query Expressions for JSON in Python
Project-URL: Documentation, https://jg-rp.github.io/python-jsonpath-rfc9535/
Project-URL: Issues, https://github.com/jg-rp/python-jsonpath-rfc9535/issues
Project-URL: Source, https://github.com/jg-rp/python-jsonpath-rfc9535
Author-email: James Prior <jamesgr.prior@gmail.com>
License-Expression: MIT
License-File: LICENSE.txt
Classifier: Development Status :: 4 - Beta
Classifier: Intended Audience :: Developers
Classifier: License :: OSI Approved :: MIT License
Classifier: Programming Language :: Python
Classifier: Programming Language :: Python :: 3.8
Classifier: Programming Language :: Python :: 3.9
Classifier: Programming Language :: Python :: 3.10
Classifier: Programming Language :: Python :: 3.11
Classifier: Programming Language :: Python :: 3.12
Classifier: Programming Language :: Python :: 3.13
Classifier: Programming Language :: Python :: Implementation :: CPython
Classifier: Programming Language :: Python :: Implementation :: PyPy
Requires-Python: >=3.8
Requires-Dist: iregexp-check>=0.1.4
Requires-Dist: regex
